ayaka_prevent_bad_words.py
nonebot_plugin_ayaka_prevent_bad_words-0.4.2.dist-info/LICENSE
nonebot_plugin_ayaka_prevent_bad_words-0.4.2.dist-info/METADATA
nonebot_plugin_ayaka_prevent_bad_words-0.4.2.dist-info/WHEEL
nonebot_plugin_ayaka_prevent_bad_words-0.4.2.dist-info/RECORD
