Metadata-Version: 2.1
Name: nonebot-plugin-ayaka-prevent-bad-words
Version: 0.4.2
Summary: 坏词撤回
Home-page: https://github.com/bridgeL/nonebot-plugin-ayaka-prevent-bad-words
License: MIT
Author: Su
Author-email: wxlxy316@163.com
Classifier: License :: OSI Approved :: MIT License
Classifier: Programming Language :: Python :: 2
Classifier: Programming Language :: Python :: 2.7
Classifier: Programming Language :: Python :: 3
Classifier: Programming Language :: Python :: 3.4
Classifier: Programming Language :: Python :: 3.5
Classifier: Programming Language :: Python :: 3.6
Classifier: Programming Language :: Python :: 3.7
Classifier: Programming Language :: Python :: 3.8
Classifier: Programming Language :: Python :: 3.9
Classifier: Programming Language :: Python :: 3.10
Classifier: Programming Language :: Python :: 3.11
Requires-Dist: ayaka (>=0.0.2.0,<0.0.4.0)
Requires-Dist: nonebot-adapter-onebot (>=2.1.5,<3.0.0)
Project-URL: Repository, https://github.com/bridgeL/nonebot-plugin-ayaka-prevent-bad-words
